rustpy_xlsxwriter-0.3.0.dist-info/METADATA
rustpy_xlsxwriter-0.3.0.dist-info/WHEEL
rustpy_xlsxwriter-0.3.0.dist-info/licenses/LICENSE
rustpy_xlsxwriter/rustpy_xlsxwriter.pyi
rustpy_xlsxwriter/__init__.py
rustpy_xlsxwriter/rustpy_xlsxwriter.cpython-312-x86_64-linux-gnu.so
rustpy_xlsxwriter-0.3.0.dist-info/RECORD
