Metadata-Version: 2.4
Name: rustpy-xlsxwriter
Version: 0.3.0
Classifier: Programming Language :: Rust
Classifier: Programming Language :: Python :: Implementation :: CPython
Classifier: Programming Language :: Python :: Implementation :: PyPy
Requires-Dist: pytest ; extra == 'tests'
Requires-Dist: xlsxwriter ; extra == 'tests'
Provides-Extra: tests
License-File: LICENSE
Summary: Rust Python bindings for rust_xlsxwriter
Home-Page: https://github.com/rahmadafandi/rustpy-xlsxwriter
Author: Rahmad Afandi <rahmadafandiii@gmail.com>
Author-email: Rahmad Afandi <rahmadafandiii@gmail.com>
License: MIT
Requires-Python: >=3.8
Project-URL: Source Code, https://github.com/rahmadafandi/rustpy-xlsxwriter
